misc/pytrade_autocomplete.sh
pytrade/__init__.py
pytrade/cli/__init__.py
pytrade/cli/arctic.py
pytrade/cli/cli.py
pytrade/cli/schedule.py
pytrade/data/__init__.py
pytrade/data/arctic.py
pytrade/data/events.py
pytrade/data/fs.py
pytrade/data/mapping.py
pytrade/data/postgres.py
pytrade/data/processing.py
pytrade/data/utils.py
pytrade/graph/__init__.py
pytrade/graph/active.py
pytrade/graph/core.py
pytrade/graph/utils.py
pytrade/neptune/__init__.py
pytrade/neptune/data.py
pytrade/neptune/graph.py
pytrade/neptune/portfolio.py
pytrade/neptune/signal.py
pytrade/neptune/utils.py
pytrade/portfolio/__init__.py
pytrade/portfolio/analysis.py
pytrade/portfolio/construction.py
pytrade/portfolio/opt.py
pytrade/portfolio/utils.py
pytrade/risk/__init__.py
pytrade/risk/realized.py
pytrade/risk/utils.py
pytrade/risk/models/__init__.py
pytrade/risk/models/analysis.py
pytrade/risk/models/cov.py
pytrade/risk/models/full.py
pytrade/risk/models/factor/__init__.py
pytrade/risk/models/factor/loadings.py
pytrade/risk/models/factor/pca.py
pytrade/risk/models/factor/returns.py
pytrade/signal/__init__.py
pytrade/signal/analysis.py
pytrade/signal/events.py
pytrade/signal/masks.py
pytrade/signal/technical.py
pytrade/signal/utils.py
pytrade/stats/__init__.py
pytrade/stats/lm.py
pytrade/stats/tests.py
pytrade/stats/utils.py
pytrade/utils/__init__.py
pytrade/utils/calendar.py
pytrade/utils/collections.py
pytrade/utils/constants.py
pytrade/utils/files.py
pytrade/utils/financials.py
pytrade/utils/functions.py
pytrade/utils/linalg.py
pytrade/utils/numpy.py
pytrade/utils/pandas.py
pytrade/utils/plotting.py
pytrade/utils/position.py
pytrade/utils/profile.py
pytrade/utils/random.py
pytrade/utils/retry.py
pytrade/utils/string.py
pytrade/utils/time.py
pytrade/utils/typing.py
pytrade/valuation/__init__.py
pytrade/valuation/dcf.py
pytrade/valuation/plotting.py
tests/__init__.py
tests/integration/__init__.py
tests/integration/graph/__init__.py
tests/unit/__init__.py
tests/unit/data/__init__.py
pytrade-0.1.0.dev20251002160504.dist-info/METADATA
pytrade-0.1.0.dev20251002160504.dist-info/WHEEL
pytrade-0.1.0.dev20251002160504.dist-info/entry_points.txt
pytrade-0.1.0.dev20251002160504.dist-info/top_level.txt
pytrade-0.1.0.dev20251002160504.dist-info/RECORD
