Metadata-Version: 2.4
Name: pytrade
Version: 0.1.0.dev20251002160504
Summary: A systematic trading framework.
Author: Jack Dry
Requires-Dist: matplotlib
Requires-Dist: cvxpy
Requires-Dist: ecos
Requires-Dist: websockets>=8.1
Requires-Dist: requests
Requires-Dist: tomli
Requires-Dist: retry
Requires-Dist: psycopg2-binary
Requires-Dist: numpy
Requires-Dist: pandas
Requires-Dist: scipy
Requires-Dist: sqlalchemy
Requires-Dist: scikit-learn
Requires-Dist: arcticdb
Requires-Dist: seaborn
Requires-Dist: pytest
Requires-Dist: tabulate
Requires-Dist: tqdm
Requires-Dist: aiohttp
Requires-Dist: networkx
Requires-Dist: selenium
Requires-Dist: xvfbwrapper
Requires-Dist: dill
Requires-Dist: regex
Requires-Dist: statsmodels
Requires-Dist: curl_cffi
Requires-Dist: ipython
Requires-Dist: s3fs
Requires-Dist: beautifulsoup4
Requires-Dist: jsmin
Requires-Dist: nltk
Requires-Dist: pycryptodome
Requires-Dist: secretstorage
Requires-Dist: pandas_market_calendars
Requires-Dist: unidecode
Requires-Dist: lxml
Requires-Dist: arelle-release
Requires-Dist: edgartools
